# This file is optional and here as an example of how to activate the build runner
# FEEL FREE TO DELETE!!

# If playing as a different race, make a file similar to this but change filename:
# `zerg_builds.yml` or `terran_builds.yml`


# Save the game opening and result to disk?
# Setting to `True` allows Ares to select a new opening after defeat
UseData: True
# How should we choose a build? Cycle is the only option for now
BuildSelection: Cycle
# For each Race / Opponent ID choose a build selection
BuildChoices:
    # test_123 is active if Debug: True (set via a `config.yml` file)
    test_123:
        BotName: Test
        Cycle:
            - TwelvePool
            - RoachRush

    Protoss:
        BotName: ProtossRace
        Cycle:
            - TwelvePool
            - RoachRush

    Random:
        BotName: RandomRace
        Cycle:
            - TwelvePool
            - RoachRush

    Terran:
        BotName: TerranRace
        Cycle:
            - TwelvePool
            - RoachRush

    Zerg:
        BotName: ZergRace
        Cycle:
            - TwelvePool
            - RoachRush

Builds:
    TwelvePool:
        # Build constant workers till x supply
        ConstantWorkerProductionTill: 0
        OpeningBuildOrder:
            - 12 overlord_scout:
                  [enemy_nat_hg_spot]
            - 12 spawningpool
            - 11 drone
            - 12 drone
            - 13 drone
            - 14 extractor
            - 13 overlord

    RoachRush:
        OpeningBuildOrder:
            - 0 overlord_scout:
                  [enemy_nat_hg_spot]
            - 0 drone
            - 0 drone
            - 0 overlord
            - 0 spawningpool
            - 0 drone
            - 0 drone
            - 0 drone
            - 0 drone
            - 0 drone
            - 0 extractor
            - 0 hatchery
            - 0 queen
            - 0 zergling
            - 0 roachwarren
            - 0 drone
            - 0 drone
            - 0 overlord
            - 0 roach
            - 0 roach
            - 0 roach
            - 0 roach
            - 0 roach
            - 0 roach
            - 0 roach
            - 0 roach